MANIFEST.in
MIT-LICENSE
README.md
VERSIONS
setup.py
bin/django-start.py
django_start/__init__.py
django_start.egg-info/PKG-INFO
django_start.egg-info/SOURCES.txt
django_start.egg-info/dependency_links.txt
django_start.egg-info/top_level.txt
django_start/management/__init__.py
django_start/management/base.py
django_start/management/importlib.py
django_start/management/utils.py
django_start/management/commands/__init__.py
django_start/management/commands/app.py
django_start/management/commands/project.py
django_start/templates/app/blog/django_start_settings.py
django_start/templates/app/blog/apps/__init__.py
django_start/templates/app/blog/apps/admin.py
django_start/templates/app/blog/apps/feeds.py
django_start/templates/app/blog/apps/models.py
django_start/templates/app/blog/apps/tests.py
django_start/templates/app/blog/apps/urls.py
django_start/templates/app/blog/apps/utils.py
django_start/templates/app/blog/apps/views.py
django_start/templates/app/blog/apps/features/blog.feature
django_start/templates/app/blog/apps/features/blog.py
django_start/templates/app/blog/apps/fixtures/development.json
django_start/templates/app/blog/templates/index.html
django_start/templates/app/blog/templates/show.html
django_start/templates/project/basic/README.md
django_start/templates/project/basic/django_start.py
django_start/templates/project/basic/deploy/requirements/base.txt
django_start/templates/project/basic/deploy/requirements/development.txt
django_start/templates/project/basic/deploy/requirements/production.txt
django_start/templates/project/basic/deploy/requirements/staging.txt
django_start/templates/project/basic/deploy/requirements/test.txt
django_start/templates/project/basic/project/__init__.py
django_start/templates/project/basic/project/manage.py
django_start/templates/project/basic/project/urls.py
django_start/templates/project/basic/project/apps/__init__.py
django_start/templates/project/basic/project/apps/ff0000/__init__.py
django_start/templates/project/basic/project/apps/ff0000/models.py
django_start/templates/project/basic/project/apps/ff0000/fixtures/README.md
