Metadata-Version: 1.0
Name: django-start
Version: 0.1.22
Summary: Create a Django project based on FF0000 best practices.
Home-page: http://github.com/ff0000/django-start/
Author: RED Interactive Agency
Author-email: claudio.baccigalupo@ff0000.com
License: UNKNOWN
Platform: UNKNOWN
Classifier: Development Status :: 3 - Alpha
Classifier: Environment :: Web Environment
Classifier: Framework :: Django
Classifier: Intended Audience :: Developers
Classifier: License :: OSI Approved :: MIT License
Classifier: Operating System :: OS Independent
Classifier: Programming Language :: Python
Classifier: Topic :: Utilities
